yz/__init__.py
yz-0.0.5.dist-info/licenses/LICENSE
yz-0.0.5.dist-info/METADATA
yz-0.0.5.dist-info/WHEEL
yz-0.0.5.dist-info/top_level.txt
yz-0.0.5.dist-info/RECORD
