Metadata-Version: 2.4
Name: yz
Version: 0.0.5
Summary: Includes various adwords elements diagnosis functions
Home-page: https://github.com/t-c-w/yz
Author: Thor Whalen
License: apache-2.0
Platform: any
License-File: LICENSE
Dynamic: license-file
